youannotate/__init__.py
youannotate-0.0.1.dist-info/LICENSE
youannotate-0.0.1.dist-info/METADATA
youannotate-0.0.1.dist-info/WHEEL
youannotate-0.0.1.dist-info/top_level.txt
youannotate-0.0.1.dist-info/RECORD
