Metadata-Version: 2.1
Name: youannotate
Version: 0.0.1
Summary: YouAnnotate
Author-email: "Karol J. Piczak" <karol@piczak.com>
License: MIT
Project-URL: Homepage, https://github.com/karolpiczak/youannotate
Project-URL: Bug Tracker, https://github.com/karolpiczak/youannotate/issues
Keywords: audio,data,annotation
Platform: any
Classifier: Programming Language :: Python :: 3.12
Classifier: License :: OSI Approved :: MIT License
Classifier: Operating System :: OS Independent
Classifier: Development Status :: 2 - Pre-Alpha
Classifier: Typing :: Typed
Classifier: Topic :: Multimedia :: Sound/Audio :: Analysis
Classifier: Topic :: Scientific/Engineering :: Artificial Intelligence
Requires-Python: >=3.12
License-File: LICENSE
Provides-Extra: dev
Requires-Dist: setuptools>=67.2; extra == "dev"
Requires-Dist: setuptools-scm[toml]>=7.1; extra == "dev"
Requires-Dist: wheel; extra == "dev"
